scheduler_tools/DaemonLauncher.py
scheduler_tools/PrefectPreferences.py
scheduler_tools/ScpDaskPrefs.py
scheduler_tools/__init__.py
scheduler_tools/aics_prefect_daemon.py
scheduler_tools/connector.py
scheduler_tools/default_dask_prefs.py
scheduler_tools/default_ssh_prefs.py
scheduler_tools/example.py
scheduler_tools/load_custom_obj.py
scheduler_tools/pbstools.py
scheduler_tools/pipelinetools.py
scheduler_tools/types.py
scheduler_tools/bin/__init__.py
scheduler_tools/bin/setup_and_spawn.bash
scheduler_tools/bin/shutdown_dask_cluster.py
scheduler_tools/bin/spawn_adaptable_dask_cluster.py
scheduler_tools/bin/spawn_dask_cluster.py
scheduler_tools/bin/stop_adaptable_dask_cluster.py
scheduler_tools/tests/__init__.py
scheduler_tools/tests/conftest.py
scheduler_tools/tests/test_PrefectPreferences.py
scheduler_tools/tests/test_connector.py
scheduler_tools/tests/test_function.py
scheduler_tools-0.1.5.data/scripts/setup_and_spawn.bash
scheduler_tools-0.1.5.dist-info/LICENSE
scheduler_tools-0.1.5.dist-info/METADATA
scheduler_tools-0.1.5.dist-info/WHEEL
scheduler_tools-0.1.5.dist-info/entry_points.txt
scheduler_tools-0.1.5.dist-info/top_level.txt
scheduler_tools-0.1.5.dist-info/RECORD
